{
  "board_size": 22,
  "parity_proved": 0,
  "target": 34,
  "child_id": 1191,
  "child_count": 2640,
  "partition": "unknown_pair_x_diag_plus_twos_x_diag_minus_twos",
  "build_seconds": 0.08065056800842285,
  "workers": 4,
  "requested_seed": 2026073391,
  "effective_seed": 2026073391,
  "main_diagonal_pair": [
    3,
    5
  ],
  "pair_index": 58,
  "diag_plus_twos": 16,
  "diag_minus_twos": 15,
  "pair_excess": 0,
  "residual_certificate_slack": 112,
  "analytic_minimum_line_defect": 46,
  "analytic_defect_details": {
    "row_costs": {
      "12": 6,
      "13": 3,
      "14": 0,
      "15": 0,
      "16": 0,
      "17": 0
    },
    "column_costs": {
      "12": 6,
      "13": 3,
      "14": 0,
      "15": 0,
      "16": 0,
      "17": 0
    },
    "plus_cost": 24,
    "minus_cost": 22,
    "row_column_minimum": 0
  },
  "maximal_line_constraints": 2455,
  "analytic_infeasible": false,
  "allowed_points": 242,
  "status": "INFEASIBLE",
  "proof_method": "cp_sat_all_lines_with_certificate_profile_cuts",
  "elapsed_seconds": 4406.214086771011,
  "branches": 45581792,
  "conflicts": 34941349
}
